{
    "capabilities":
        [
            {
                "browserName": "firefox",
                "version": "10",
                "firefox_binary": "/Applications/Firefox 10.app/Contents/MacOS/firefox-bin",
                "platform": "MAC",
                "maxInstances": 1,
                "seleniumProtocol": "WebDriver"
            }, {
                "browserName": "firefox",
                "version": "12",
                "firefox_binary": "/Applications/Firefox 12.app/Contents/MacOS/firefox-bin",
                "platform": "MAC",
                "maxInstances": 1,
                "seleniumProtocol": "WebDriver"
            }, {
                "browserName": "firefox",
                "version": "13",
                "firefox_binary": "/Applications/Firefox 13.app/Contents/MacOS/firefox-bin",
                "platform": "MAC",
                "maxInstances": 1,
                "seleniumProtocol": "WebDriver"
            }, {
                "browserName": "firefox",
                "version": "14",
                "firefox_binary": "/Applications/Firefox 14.app/Contents/MacOS/firefox-bin",
                "platform": "MAC",
                "maxInstances": 1,
                "seleniumProtocol": "WebDriver"
            }, {
                "browserName": "firefox",
                "version": "beta",
                "firefox_binary": "/Applications/Firefox Beta.app/Contents/MacOS/firefox-bin",
                "platform": "MAC",
                "maxInstances": 1,
                "seleniumProtocol": "WebDriver"
            }, {
                "browserName": "firefox",
                "version": "aurora",
                "firefox_binary": "/Applications/Aurora.app/Contents/MacOS/firefox-bin",
                "platform": "MAC",
                "maxInstances": 1,
                "seleniumProtocol": "WebDriver"
            }, {
                "browserName": "firefox",
                "version": "nightly",
                "firefox_binary": "/Applications/Nightly.app/Contents/MacOS/firefox-bin",
                "platform": "MAC",
                "maxInstances": 1,
                "seleniumProtocol": "WebDriver"
            }
        ],
    "configuration": {}
}
